owoi_audio_to_clip/ClipMakerFactory.py
owoi_audio_to_clip/TranscriptFactory.py
owoi_audio_to_clip/WordTimestamp.py
owoi_audio_to_clip/__init__.py
owoi_audio_to_clip/utils.py
owoi_audiotoclip-1.2.0.dist-info/WHEEL
owoi_audiotoclip-1.2.0.dist-info/METADATA
owoi_audiotoclip-1.2.0.dist-info/RECORD
