Metadata-Version: 2.1
Name: owoi-audiotoclip
Version: 1.2.0
Summary: Package to convert audio to video with google speech to text and google image search
License: MIT
Author: Pierre-Louis Sergent
Author-email: papa.louis59@gmail.com
Requires-Python: >=3.9,<4.0
Classifier: License :: OSI Approved :: MIT License
Classifier: Programming Language :: Python :: 3
Classifier: Programming Language :: Python :: 3.9
Classifier: Programming Language :: Python :: 3.10
Requires-Dist: Google-Images-Search (>=1.4.6,<2.0.0)
Requires-Dist: black (>=22.10.0,<23.0.0)
Requires-Dist: google-cloud-speech (>=2.16.2,<3.0.0)
Requires-Dist: google-cloud-storage (>=2.5.0,<3.0.0)
Requires-Dist: imageio[opencv] (>=2.25.1,<3.0.0)
Requires-Dist: moviepy (>=1.0.3,<2.0.0)
Requires-Dist: pytube (>=12.1.2,<13.0.0)
